pyzub/__init__.py
pyzub/cli.py
pyzub/subexceptions.py
pyzub/subfiles.py
pyzub/utils.py
pyzub-0.1.6.dist-info/METADATA
pyzub-0.1.6.dist-info/RECORD
pyzub-0.1.6.dist-info/WHEEL
pyzub-0.1.6.dist-info/entry_points.txt
pyzub-0.1.6.dist-info/top_level.txt
