Metadata-Version: 2.1
Name: pyzub
Version: 0.1.6
Summary: A small package and CLI for manipulating and creating subtitles (SubRip, .srt, etc.)
Home-page: https://github.com/nicolascerna/pyzub
Author: Nicolás Cerna
Author-email: nicolascerna@uc.cl
License: UNKNOWN
Platform: UNKNOWN
Classifier: Programming Language :: Python :: 3
Classifier: License :: OSI Approved :: MIT License
Classifier: Operating System :: OS Independent
Requires-Python: >=3.0
Requires-Dist: Click
Requires-Dist: chardet
Requires-Dist: tqdm
